[
  {
    "line": 4,
    "elements": [
      {
        "before": [
          {
            "result": {
              "duration": 77732900,
              "status": "passed"
            },
            "match": {
              "location": "PreparacionEscenario.sepUp()"
            }
          }
        ],
        "line": 10,
        "name": "Validar el inicio de sesion exitoso",
        "description": "",
        "id": "loguearse-en-la-pagina-sport10;validar-el-inicio-de-sesion-exitoso",
        "type": "scenario",
        "keyword": "Escenario",
        "steps": [
          {
            "result": {
              "duration": 5950569600,
              "status": "passed"
            },
            "line": 11,
            "name": "que el administrador este en la pagina",
            "match": {
              "location": "LoginStepDefinition.queElAdministradorEsteEnLaPagina()"
            },
            "keyword": "Dado "
          },
          {
            "result": {
              "duration": 3663889100,
              "status": "passed"
            },
            "line": 12,
            "name": "ingrese las crendenciales para loguearse:",
            "match": {
              "location": "LoginStepDefinition.ingreseLasCrendencialesParaLoguearse(DatosLogin\u003e)"
            },
            "rows": [
              {
                "cells": [
                  "email",
                  "password"
                ]
              },
              {
                "cells": [
                  "felipe@gmail.com",
                  "skjdahkjshdu13432.,-"
                ]
              }
            ],
            "keyword": "Cuando "
          },
          {
            "result": {
              "error_message": "net.thucydides.core.webdriver.exceptions.ElementShouldBeEnabledException: Expected enabled element was not enabled\r\n\tat net.serenitybdd.core.pages.WebElementFacadeImpl.waitUntilEnabled(WebElementFacadeImpl.java:1149)\r\n\tat net.serenitybdd.core.pages.WebElementFacadeImpl.waitUntilElementAvailable(WebElementFacadeImpl.java:954)\r\n\tat net.serenitybdd.core.pages.WebElementFacadeImpl.click(WebElementFacadeImpl.java:1229)\r\n\tat net.serenitybdd.screenplay.actions.ClickOnTarget.performAs(ClickOnTarget.java:13)\r\n\tat net.serenitybdd.screenplay.actions.ClickOnTarget$ByteBuddy$0JE2mIUy.performAs$accessor$Ne0CTMSH(Unknown Source)\r\n\tat java.base/jdk.internal.reflect.NativeMethodAccessorImpl.invoke0(Native Method)\r\n\tat java.base/jdk.internal.reflect.NativeMethodAccessorImpl.invoke(NativeMethodAccessorImpl.java:64)\r\n\tat java.base/jdk.internal.reflect.DelegatingMethodAccessorImpl.invoke(DelegatingMethodAccessorImpl.java:43)\r\n\tat java.base/java.lang.reflect.Method.invoke(Method.java:564)\r\n\tat net.thucydides.core.steps.StepInterceptor.invokeMethod(StepInterceptor.java:488)\r\n\tat net.thucydides.core.steps.StepInterceptor.executeTestStepMethod(StepInterceptor.java:468)\r\n\tat net.thucydides.core.steps.StepInterceptor.runTestStep(StepInterceptor.java:441)\r\n\tat net.thucydides.core.steps.StepInterceptor.runOrSkipMethod(StepInterceptor.java:197)\r\n\tat net.thucydides.core.steps.StepInterceptor.testStepResult(StepInterceptor.java:184)\r\n\tat net.thucydides.core.steps.StepInterceptor.intercept(StepInterceptor.java:77)\r\n\tat net.serenitybdd.screenplay.actions.ClickOnTarget$ByteBuddy$0JE2mIUy.performAs(Unknown Source)\r\n\tat net.serenitybdd.screenplay.Actor.performTask(Actor.java:248)\r\n\tat net.serenitybdd.screenplay.Actor.perform(Actor.java:229)\r\n\tat net.serenitybdd.screenplay.Actor.attemptsTo(Actor.java:175)\r\n\tat co.com.Automatizacion.userinterface.venta.ClickEnConsultarVenta.performAs(ClickEnConsultarVenta.java:18)\r\n\tat co.com.Automatizacion.userinterface.venta.ClickEnConsultarVenta$ByteBuddy$GbfmZBDE.performAs$accessor$KZAxBdAs(Unknown Source)\r\n\tat java.base/jdk.internal.reflect.NativeMethodAccessorImpl.invoke0(Native Method)\r\n\tat java.base/jdk.internal.reflect.NativeMethodAccessorImpl.invoke(NativeMethodAccessorImpl.java:64)\r\n\tat java.base/jdk.internal.reflect.DelegatingMethodAccessorImpl.invoke(DelegatingMethodAccessorImpl.java:43)\r\n\tat java.base/java.lang.reflect.Method.invoke(Method.java:564)\r\n\tat net.thucydides.core.steps.StepInterceptor.invokeMethod(StepInterceptor.java:488)\r\n\tat net.thucydides.core.steps.StepInterceptor.executeTestStepMethod(StepInterceptor.java:468)\r\n\tat net.thucydides.core.steps.StepInterceptor.runTestStep(StepInterceptor.java:441)\r\n\tat net.thucydides.core.steps.StepInterceptor.runOrSkipMethod(StepInterceptor.java:197)\r\n\tat net.thucydides.core.steps.StepInterceptor.testStepResult(StepInterceptor.java:184)\r\n\tat net.thucydides.core.steps.StepInterceptor.intercept(StepInterceptor.java:77)\r\n\tat co.com.Automatizacion.userinterface.venta.ClickEnConsultarVenta$ByteBuddy$GbfmZBDE.performAs(Unknown Source)\r\n\tat net.serenitybdd.screenplay.Actor.performTask(Actor.java:248)\r\n\tat net.serenitybdd.screenplay.Actor.perform(Actor.java:229)\r\n\tat net.serenitybdd.screenplay.Actor.attemptsTo(Actor.java:175)\r\n\tat co.com.Automatizacion.stepsdefinitions.venta.PaginaStepDefinition.elAdministradorHaceClickEnVenta(PaginaStepDefinition.java:20)\r\n\tat ✽.el administrador hace click en Venta(src/test/resources/features/venta/venta.feature:15)\r\nCaused by: org.openqa.selenium.TimeoutException: Expected condition failed: waiting for By.xpath: //img[contains(@src,\u002714255792.gif\u0027)] to be enabled (tried for 5 second(s) with 100 milliseconds interval)\r\n\tat org.openqa.selenium.support.ui.FluentWait.timeoutException(FluentWait.java:304)\r\n\tat org.openqa.selenium.support.ui.FluentWait.until(FluentWait.java:272)\r\n\tat net.serenitybdd.core.pages.WebElementFacadeImpl.waitUntilEnabled(WebElementFacadeImpl.java:1146)\r\n\tat net.serenitybdd.core.pages.WebElementFacadeImpl.waitUntilElementAvailable(WebElementFacadeImpl.java:954)\r\n\tat net.serenitybdd.core.pages.WebElementFacadeImpl.click(WebElementFacadeImpl.java:1229)\r\n\tat net.serenitybdd.screenplay.actions.ClickOnTarget.performAs(ClickOnTarget.java:13)\r\n\tat net.serenitybdd.screenplay.actions.ClickOnTarget$ByteBuddy$0JE2mIUy.performAs$accessor$Ne0CTMSH(Unknown Source)\r\n\tat java.base/jdk.internal.reflect.NativeMethodAccessorImpl.invoke0(Native Method)\r\n\tat java.base/jdk.internal.reflect.NativeMethodAccessorImpl.invoke(NativeMethodAccessorImpl.java:64)\r\n\tat java.base/jdk.internal.reflect.DelegatingMethodAccessorImpl.invoke(DelegatingMethodAccessorImpl.java:43)\r\n\tat java.base/java.lang.reflect.Method.invoke(Method.java:564)\r\n\tat net.thucydides.core.steps.StepInterceptor.invokeMethod(StepInterceptor.java:488)\r\n\tat net.thucydides.core.steps.StepInterceptor.executeTestStepMethod(StepInterceptor.java:468)\r\n\tat net.thucydides.core.steps.StepInterceptor.runTestStep(StepInterceptor.java:441)\r\n\tat net.thucydides.core.steps.StepInterceptor.runOrSkipMethod(StepInterceptor.java:197)\r\n\tat net.thucydides.core.steps.StepInterceptor.testStepResult(StepInterceptor.java:184)\r\n\tat net.thucydides.core.steps.StepInterceptor.intercept(StepInterceptor.java:77)\r\n\tat net.serenitybdd.screenplay.actions.ClickOnTarget$ByteBuddy$0JE2mIUy.performAs(Unknown Source)\r\n\tat net.serenitybdd.screenplay.Actor.performTask(Actor.java:248)\r\n\tat net.serenitybdd.screenplay.Actor.perform(Actor.java:229)\r\n\tat net.serenitybdd.screenplay.Actor.attemptsTo(Actor.java:175)\r\n\tat co.com.Automatizacion.userinterface.venta.ClickEnConsultarVenta.performAs(ClickEnConsultarVenta.java:18)\r\n\tat co.com.Automatizacion.userinterface.venta.ClickEnConsultarVenta$ByteBuddy$GbfmZBDE.performAs$accessor$KZAxBdAs(Unknown Source)\r\n\tat java.base/jdk.internal.reflect.NativeMethodAccessorImpl.invoke0(Native Method)\r\n\tat java.base/jdk.internal.reflect.NativeMethodAccessorImpl.invoke(NativeMethodAccessorImpl.java:64)\r\n\tat java.base/jdk.internal.reflect.DelegatingMethodAccessorImpl.invoke(DelegatingMethodAccessorImpl.java:43)\r\n\tat java.base/java.lang.reflect.Method.invoke(Method.java:564)\r\n\tat net.thucydides.core.steps.StepInterceptor.invokeMethod(StepInterceptor.java:488)\r\n\tat net.thucydides.core.steps.StepInterceptor.executeTestStepMethod(StepInterceptor.java:468)\r\n\tat net.thucydides.core.steps.StepInterceptor.runTestStep(StepInterceptor.java:441)\r\n\tat net.thucydides.core.steps.StepInterceptor.runOrSkipMethod(StepInterceptor.java:197)\r\n\tat net.thucydides.core.steps.StepInterceptor.testStepResult(StepInterceptor.java:184)\r\n\tat net.thucydides.core.steps.StepInterceptor.intercept(StepInterceptor.java:77)\r\n\tat co.com.Automatizacion.userinterface.venta.ClickEnConsultarVenta$ByteBuddy$GbfmZBDE.performAs(Unknown Source)\r\n\tat net.serenitybdd.screenplay.Actor.performTask(Actor.java:248)\r\n\tat net.serenitybdd.screenplay.Actor.perform(Actor.java:229)\r\n\tat net.serenitybdd.screenplay.Actor.attemptsTo(Actor.java:175)\r\n\tat co.com.Automatizacion.stepsdefinitions.venta.PaginaStepDefinition.elAdministradorHaceClickEnVenta(PaginaStepDefinition.java:20)\r\n\tat java.base/jdk.internal.reflect.NativeMethodAccessorImpl.invoke0(Native Method)\r\n\tat java.base/jdk.internal.reflect.NativeMethodAccessorImpl.invoke(NativeMethodAccessorImpl.java:64)\r\n\tat java.base/jdk.internal.reflect.DelegatingMethodAccessorImpl.invoke(DelegatingMethodAccessorImpl.java:43)\r\n\tat java.base/java.lang.reflect.Method.invoke(Method.java:564)\r\n\tat cucumber.runtime.Utils$1.call(Utils.java:31)\r\n\tat cucumber.runtime.Timeout.timeout(Timeout.java:16)\r\n\tat cucumber.runtime.Utils.invoke(Utils.java:25)\r\n\tat cucumber.runtime.java.JavaStepDefinition.execute(JavaStepDefinition.java:37)\r\n\tat cucumber.runtime.StepDefinitionMatch.runStep(StepDefinitionMatch.java:40)\r\n\tat cucumber.api.TestStep.executeStep(TestStep.java:102)\r\n\tat cucumber.api.TestStep.run(TestStep.java:83)\r\n\tat cucumber.api.TestCase.run(TestCase.java:58)\r\n\tat cucumber.runner.Runner.runPickle(Runner.java:80)\r\n\tat cucumber.runtime.junit.PickleRunners$NoStepDescriptions.run(PickleRunners.java:140)\r\n\tat cucumber.runtime.junit.FeatureRunner.runChild(FeatureRunner.java:68)\r\n\tat cucumber.runtime.junit.FeatureRunner.runChild(FeatureRunner.java:23)\r\n\tat org.junit.runners.ParentRunner$3.run(ParentRunner.java:290)\r\n\tat org.junit.runners.ParentRunner$1.schedule(ParentRunner.java:71)\r\n\tat org.junit.runners.ParentRunner.runChildren(ParentRunner.java:288)\r\n\tat org.junit.runners.ParentRunner.access$000(ParentRunner.java:58)\r\n\tat org.junit.runners.ParentRunner$2.evaluate(ParentRunner.java:268)\r\n\tat org.junit.runners.ParentRunner.run(ParentRunner.java:363)\r\n\tat cucumber.runtime.junit.FeatureRunner.run(FeatureRunner.java:73)\r\n\tat cucumber.api.junit.Cucumber.runChild(Cucumber.java:118)\r\n\tat cucumber.api.junit.Cucumber.runChild(Cucumber.java:56)\r\n\tat org.junit.runners.ParentRunner$3.run(ParentRunner.java:290)\r\n\tat org.junit.runners.ParentRunner$1.schedule(ParentRunner.java:71)\r\n\tat org.junit.runners.ParentRunner.runChildren(ParentRunner.java:288)\r\n\tat org.junit.runners.ParentRunner.access$000(ParentRunner.java:58)\r\n\tat org.junit.runners.ParentRunner$2.evaluate(ParentRunner.java:268)\r\n\tat cucumber.api.junit.Cucumber$1.evaluate(Cucumber.java:127)\r\n\tat org.junit.runners.ParentRunner.run(ParentRunner.java:363)\r\n\tat org.gradle.api.internal.tasks.testing.junit.JUnitTestClassExecutor.runTestClass(JUnitTestClassExecutor.java:112)\r\n\tat org.gradle.api.internal.tasks.testing.junit.JUnitTestClassExecutor.execute(JUnitTestClassExecutor.java:58)\r\n\tat org.gradle.api.internal.tasks.testing.junit.JUnitTestClassExecutor.execute(JUnitTestClassExecutor.java:40)\r\n\tat org.gradle.api.internal.tasks.testing.junit.AbstractJUnitTestClassProcessor.processTestClass(AbstractJUnitTestClassProcessor.java:54)\r\n\tat org.gradle.api.internal.tasks.testing.SuiteTestClassProcessor.processTestClass(SuiteTestClassProcessor.java:53)\r\n\tat java.base/jdk.internal.reflect.NativeMethodAccessorImpl.invoke0(Native Method)\r\n\tat java.base/jdk.internal.reflect.NativeMethodAccessorImpl.invoke(NativeMethodAccessorImpl.java:64)\r\n\tat java.base/jdk.internal.reflect.DelegatingMethodAccessorImpl.invoke(DelegatingMethodAccessorImpl.java:43)\r\n\tat java.base/java.lang.reflect.Method.invoke(Method.java:564)\r\n\tat org.gradle.internal.dispatch.ReflectionDispatch.dispatch(ReflectionDispatch.java:36)\r\n\tat org.gradle.internal.dispatch.ReflectionDispatch.dispatch(ReflectionDispatch.java:24)\r\n\tat org.gradle.internal.dispatch.ContextClassLoaderDispatch.dispatch(ContextClassLoaderDispatch.java:33)\r\n\tat org.gradle.internal.dispatch.ProxyDispatchAdapter$DispatchingInvocationHandler.invoke(ProxyDispatchAdapter.java:92)\r\n\tat com.sun.proxy.$Proxy4.processTestClass(Unknown Source)\r\n\tat org.gradle.api.internal.tasks.testing.worker.TestWorker$2.run(TestWorker.java:183)\r\n\tat org.gradle.api.internal.tasks.testing.worker.TestWorker.executeAndMaintainThreadName(TestWorker.java:132)\r\n\tat org.gradle.api.internal.tasks.testing.worker.TestWorker.execute(TestWorker.java:103)\r\n\tat org.gradle.api.internal.tasks.testing.worker.TestWorker.execute(TestWorker.java:63)\r\n\tat org.gradle.process.internal.worker.child.ActionExecutionWorker.execute(ActionExecutionWorker.java:56)\r\n\tat org.gradle.process.internal.worker.child.SystemApplicationClassLoaderWorker.call(SystemApplicationClassLoaderWorker.java:121)\r\n\tat org.gradle.process.internal.worker.child.SystemApplicationClassLoaderWorker.call(SystemApplicationClassLoaderWorker.java:71)\r\n\tat worker.org.gradle.process.internal.worker.GradleWorkerMain.run(GradleWorkerMain.java:69)\r\n\tat worker.org.gradle.process.internal.worker.GradleWorkerMain.main(GradleWorkerMain.java:74)\r\nCaused by: org.openqa.selenium.NoSuchElementException: no such element: Unable to locate element: {\"method\":\"xpath\",\"selector\":\"//img[contains(@src,\u002714255792.gif\u0027)]\"}\n  (Session info: chrome\u003d142.0.7444.61)\nFor documentation on this error, please visit: https://www.seleniumhq.org/exceptions/no_such_element.html\nBuild info: version: \u00273.141.59\u0027, revision: \u0027e82be7d358\u0027, time: \u00272018-11-14T08:17:03\u0027\nSystem info: host: \u0027CALLCENTER-060\u0027, ip: \u0027192.168.112.18\u0027, os.name: \u0027Windows 10\u0027, os.arch: \u0027amd64\u0027, os.version: \u002710.0\u0027, java.version: \u002715.0.2\u0027\nDriver info: org.openqa.selenium.chrome.ChromeDriver\nCapabilities {acceptInsecureCerts: false, browserName: chrome, browserVersion: 142.0.7444.61, chrome: {chromedriverVersion: 142.0.7444.59 (4b8153ab58d3..., userDataDir: C:\\Users\\APREND~1.SEN\\AppDa...}, fedcm:accounts: true, goog:chromeOptions: {debuggerAddress: localhost:53606}, goog:processID: 46392, javascriptEnabled: true, networkConnectionEnabled: false, pageLoadStrategy: normal, platform: WINDOWS, platformName: WINDOWS, proxy: Proxy(), setWindowRect: true, strictFileInteractability: false, timeouts: {implicit: 0, pageLoad: 300000, script: 30000}, unhandledPromptBehavior: ignore, webauthn:extension:credBlob: true, webauthn:extension:largeBlob: true, webauthn:extension:minPinLength: true, webauthn:extension:prf: true, webauthn:virtualAuthenticators: true}\nSession ID: 9c113c6c6e0cef5aafc0038409dcf665\n*** Element info: {Using\u003dxpath, value\u003d//img[contains(@src,\u002714255792.gif\u0027)]}\r\n\tat java.base/jdk.internal.reflect.NativeConstructorAccessorImpl.newInstance0(Native Method)\r\n\tat java.base/jdk.internal.reflect.NativeConstructorAccessorImpl.newInstance(NativeConstructorAccessorImpl.java:64)\r\n\tat java.base/jdk.internal.reflect.DelegatingConstructorAccessorImpl.newInstance(DelegatingConstructorAccessorImpl.java:45)\r\n\tat java.base/java.lang.reflect.Constructor.newInstanceWithCaller(Constructor.java:500)\r\n\tat java.base/java.lang.reflect.Constructor.newInstance(Constructor.java:481)\r\n\tat org.openqa.selenium.remote.http.W3CHttpResponseCodec.createException(W3CHttpResponseCodec.java:187)\r\n\tat org.openqa.selenium.remote.http.W3CHttpResponseCodec.decode(W3CHttpResponseCodec.java:122)\r\n\tat org.openqa.selenium.remote.http.W3CHttpResponseCodec.decode(W3CHttpResponseCodec.java:49)\r\n\tat org.openqa.selenium.remote.HttpCommandExecutor.execute(HttpCommandExecutor.java:158)\r\n\tat org.openqa.selenium.remote.service.DriverCommandExecutor.execute(DriverCommandExecutor.java:83)\r\n\tat org.openqa.selenium.remote.RemoteWebDriver.execute(RemoteWebDriver.java:552)\r\n\tat org.openqa.selenium.remote.RemoteWebDriver.findElement(RemoteWebDriver.java:323)\r\n\tat org.openqa.selenium.remote.RemoteWebDriver.findElementByXPath(RemoteWebDriver.java:428)\r\n\tat org.openqa.selenium.By$ByXPath.findElement(By.java:353)\r\n\tat org.openqa.selenium.remote.RemoteWebDriver.findElement(RemoteWebDriver.java:315)\r\n\tat net.thucydides.core.webdriver.WebDriverFacade.findElement(WebDriverFacade.java:222)\r\n\tat net.serenitybdd.core.pages.WebElementResolverByLocator.resolveForDriver(WebElementResolverByLocator.java:18)\r\n\tat net.serenitybdd.core.pages.WebElementFacadeImpl.getElement(WebElementFacadeImpl.java:221)\r\n\tat net.serenitybdd.core.pages.WebElementExpectations$3.apply(WebElementExpectations.java:63)\r\n\tat net.serenitybdd.core.pages.WebElementExpectations$3.apply(WebElementExpectations.java:55)\r\n\tat org.openqa.selenium.support.ui.FluentWait.until(FluentWait.java:249)\r\n\t... 91 more\r\n",
              "duration": 6977353600,
              "status": "failed"
            },
            "line": 15,
            "name": "el administrador hace click en Venta",
            "match": {
              "location": "PaginaStepDefinition.elAdministradorHaceClickEnVenta()"
            },
            "keyword": "Y "
          },
          {
            "result": {
              "status": "skipped"
            },
            "line": 16,
            "name": "el administrador hace click en Consultar venta",
            "match": {
              "location": "PaginaStepDefinition.elAdministradorHaceClickEnConsultarVenta()"
            },
            "keyword": "Y "
          },
          {
            "result": {
              "status": "skipped"
            },
            "line": 17,
            "name": "el administrador vuelve atras",
            "match": {
              "location": "PaginaStepDefinition.elAdministradorVuelveAtras()"
            },
            "keyword": "Y "
          },
          {
            "result": {
              "status": "skipped"
            },
            "line": 18,
            "name": "el administrador hace click en Crear venta",
            "match": {
              "location": "PaginaStepDefinition.elAdministradorHaceClickEnCrearVenta()"
            },
            "keyword": "Y "
          },
          {
            "result": {
              "status": "skipped"
            },
            "line": 19,
            "name": "el administrador llena el formulario de venta:",
            "match": {
              "location": "PaginaStepDefinition.elAdministradorLlenaElFormularioDeVenta(DataTable)"
            },
            "rows": [
              {
                "cells": [
                  "nombre_cli",
                  "direccion_cli",
                  "correo_cli",
                  "num_tel_cli",
                  "num_doc_cli",
                  "referencia",
                  "cantidad",
                  "vendedor"
                ]
              },
              {
                "cells": [
                  "Mateo Garcia",
                  "Calle 100",
                  "mateo@test.com",
                  "3015551111",
                  "123456789",
                  "1",
                  "2",
                  "2"
                ]
              }
            ],
            "keyword": "Y "
          },
          {
            "result": {
              "status": "skipped"
            },
            "line": 22,
            "name": "el administrador vuelve a consultar venta",
            "match": {
              "location": "PaginaStepDefinition.elAdministradorVuelveAConsultarVenta()"
            },
            "keyword": "Y "
          },
          {
            "result": {
              "status": "skipped"
            },
            "line": 23,
            "name": "el administrador hace click en la imagen de venta",
            "match": {
              "location": "PaginaStepDefinition.elAdministradorHaceClickEnLaImagenDeVenta()"
            },
            "keyword": "Y "
          },
          {
            "result": {
              "status": "skipped"
            },
            "line": 24,
            "name": "Se debe verificar que el administrador haya ingresado correctamente a la página y tenga acceso a sus funciones",
            "match": {
              "location": "LoginStepDefinition.seDebeVerificarQueElAdministradorHayaIngresadoCorrectamenteALaPáginaYTengaAccesoASusFunciones()"
            },
            "keyword": "Entonces "
          }
        ],
        "tags": [
          {
            "name": "@Login"
          }
        ]
      }
    ],
    "name": "Loguearse en la pagina Sport10",
    "description": "  Como administrador de la pagina Sport10\n  Quiero loguearme con las credenciales asignadas\n  Para tener acceso a las funciones de gestion de inventario y usuarios",
    "id": "loguearse-en-la-pagina-sport10",
    "keyword": "Característica",
    "uri": "src/test/resources/features/venta/venta.feature",
    "tags": []
  }
]